[
    {
        "mahalleKayitNo": 147079,
        "turKod": 4,
        "bilesenAdi": "5550 (Sokak)",
        "adi": "5550",
        "kimlikNo": 876627481
    },
    {
        "mahalleKayitNo": 147079,
        "turKod": 4,
        "bilesenAdi": "ATATEPE SANAYİ SİTESİ 1. (Sokak)",
        "adi": "ATATEPE SANAYİ SİTESİ 1.",
        "kimlikNo": 898238
    },
    {
        "mahalleKayitNo": 147079,
        "turKod": 4,
        "bilesenAdi": "ATATEPE SANAYİ SİTESİ 10. (Sokak)",
        "adi": "ATATEPE SANAYİ SİTESİ 10.",
        "kimlikNo": 897020
    },
    {
        "mahalleKayitNo": 147079,
        "turKod": 4,
        "bilesenAdi": "ATATEPE SANAYİ SİTESİ 11. (Sokak)",
        "adi": "ATATEPE SANAYİ SİTESİ 11.",
        "kimlikNo": 897021
    },
    {
        "mahalleKayitNo": 147079,
        "turKod": 4,
        "bilesenAdi": "ATATEPE SANAYİ SİTESİ 12. (Sokak)",
        "adi": "ATATEPE SANAYİ SİTESİ 12.",
        "kimlikNo": 898245
    },
    {
        "mahalleKayitNo": 147079,
        "turKod": 4,
        "bilesenAdi": "ATATEPE SANAYİ SİTESİ 13. (Sokak)",
        "adi": "ATATEPE SANAYİ SİTESİ 13.",
        "kimlikNo": 897022
    },
    {
        "mahalleKayitNo": 147079,
        "turKod": 4,
        "bilesenAdi": "ATATEPE SANAYİ SİTESİ 14. (Sokak)",
        "adi": "ATATEPE SANAYİ SİTESİ 14.",
        "kimlikNo": 897023
    },
    {
        "mahalleKayitNo": 147079,
        "turKod": 4,
        "bilesenAdi": "ATATEPE SANAYİ SİTESİ 15. (Sokak)",
        "adi": "ATATEPE SANAYİ SİTESİ 15.",
        "kimlikNo": 898248
    },
    {
        "mahalleKayitNo": 147079,
        "turKod": 4,
        "bilesenAdi": "ATATEPE SANAYİ SİTESİ 16. (Sokak)",
        "adi": "ATATEPE SANAYİ SİTESİ 16.",
        "kimlikNo": 897026
    },
    {
        "mahalleKayitNo": 147079,
        "turKod": 4,
        "bilesenAdi": "ATATEPE SANAYİ SİTESİ 17. (Sokak)",
        "adi": "ATATEPE SANAYİ SİTESİ 17.",
        "kimlikNo": 897027
    },
    {
        "mahalleKayitNo": 147079,
        "turKod": 4,
        "bilesenAdi": "ATATEPE SANAYİ SİTESİ 18. (Sokak)",
        "adi": "ATATEPE SANAYİ SİTESİ 18.",
        "kimlikNo": 898249
    },
    {
        "mahalleKayitNo": 147079,
        "turKod": 4,
        "bilesenAdi": "ATATEPE SANAYİ SİTESİ 19. (Sokak)",
        "adi": "ATATEPE SANAYİ SİTESİ 19.",
        "kimlikNo": 898250
    },
    {
        "mahalleKayitNo": 147079,
        "turKod": 4,
        "bilesenAdi": "ATATEPE SANAYİ SİTESİ 2. (Sokak)",
        "adi": "ATATEPE SANAYİ SİTESİ 2.",
        "kimlikNo": 898239
    },
    {
        "mahalleKayitNo": 147079,
        "turKod": 4,
        "bilesenAdi": "ATATEPE SANAYİ SİTESİ 20. (Sokak)",
        "adi": "ATATEPE SANAYİ SİTESİ 20.",
        "kimlikNo": 898251
    },
    {
        "mahalleKayitNo": 147079,
        "turKod": 4,
        "bilesenAdi": "ATATEPE SANAYİ SİTESİ 21. (Sokak)",
        "adi": "ATATEPE SANAYİ SİTESİ 21.",
        "kimlikNo": 897029
    },
    {
        "mahalleKayitNo": 147079,
        "turKod": 4,
        "bilesenAdi": "ATATEPE SANAYİ SİTESİ 22. (Sokak)",
        "adi": "ATATEPE SANAYİ SİTESİ 22.",
        "kimlikNo": 898252
    },
    {
        "mahalleKayitNo": 147079,
        "turKod": 4,
        "bilesenAdi": "ATATEPE SANAYİ SİTESİ 23. (Sokak)",
        "adi": "ATATEPE SANAYİ SİTESİ 23.",
        "kimlikNo": 898253
    },
    {
        "mahalleKayitNo": 147079,
        "turKod": 4,
        "bilesenAdi": "ATATEPE SANAYİ SİTESİ 24. (Sokak)",
        "adi": "ATATEPE SANAYİ SİTESİ 24.",
        "kimlikNo": 898254
    },
    {
        "mahalleKayitNo": 147079,
        "turKod": 4,
        "bilesenAdi": "ATATEPE SANAYİ SİTESİ 25. (Sokak)",
        "adi": "ATATEPE SANAYİ SİTESİ 25.",
        "kimlikNo": 897030
    },
    {
        "mahalleKayitNo": 147079,
        "turKod": 4,
        "bilesenAdi": "ATATEPE SANAYİ SİTESİ 26. (Sokak)",
        "adi": "ATATEPE SANAYİ SİTESİ 26.",
        "kimlikNo": 897031
    },
    {
        "mahalleKayitNo": 147079,
        "turKod": 4,
        "bilesenAdi": "ATATEPE SANAYİ SİTESİ 27. (Sokak)",
        "adi": "ATATEPE SANAYİ SİTESİ 27.",
        "kimlikNo": 897032
    },
    {
        "mahalleKayitNo": 147079,
        "turKod": 4,
        "bilesenAdi": "ATATEPE SANAYİ SİTESİ 28. (Sokak)",
        "adi": "ATATEPE SANAYİ SİTESİ 28.",
        "kimlikNo": 898257
    },
    {
        "mahalleKayitNo": 147079,
        "turKod": 4,
        "bilesenAdi": "ATATEPE SANAYİ SİTESİ 29. (Sokak)",
        "adi": "ATATEPE SANAYİ SİTESİ 29.",
        "kimlikNo": 898258
    },
    {
        "mahalleKayitNo": 147079,
        "turKod": 4,
        "bilesenAdi": "ATATEPE SANAYİ SİTESİ 3. (Sokak)",
        "adi": "ATATEPE SANAYİ SİTESİ 3.",
        "kimlikNo": 897015
    },
    {
        "mahalleKayitNo": 147079,
        "turKod": 4,
        "bilesenAdi": "ATATEPE SANAYİ SİTESİ 30. (Sokak)",
        "adi": "ATATEPE SANAYİ SİTESİ 30.",
        "kimlikNo": 898259
    },
    {
        "mahalleKayitNo": 147079,
        "turKod": 4,
        "bilesenAdi": "ATATEPE SANAYİ SİTESİ 31. (Sokak)",
        "adi": "ATATEPE SANAYİ SİTESİ 31.",
        "kimlikNo": 898261
    },
    {
        "mahalleKayitNo": 147079,
        "turKod": 4,
        "bilesenAdi": "ATATEPE SANAYİ SİTESİ 32. (Sokak)",
        "adi": "ATATEPE SANAYİ SİTESİ 32.",
        "kimlikNo": 898262
    },
    {
        "mahalleKayitNo": 147079,
        "turKod": 4,
        "bilesenAdi": "ATATEPE SANAYİ SİTESİ 33. (Sokak)",
        "adi": "ATATEPE SANAYİ SİTESİ 33.",
        "kimlikNo": 897033
    },
    {
        "mahalleKayitNo": 147079,
        "turKod": 4,
        "bilesenAdi": "ATATEPE SANAYİ SİTESİ 34. (Sokak)",
        "adi": "ATATEPE SANAYİ SİTESİ 34.",
        "kimlikNo": 898263
    },
    {
        "mahalleKayitNo": 147079,
        "turKod": 4,
        "bilesenAdi": "ATATEPE SANAYİ SİTESİ 35. (Sokak)",
        "adi": "ATATEPE SANAYİ SİTESİ 35.",
        "kimlikNo": 898264
    },
    {
        "mahalleKayitNo": 147079,
        "turKod": 4,
        "bilesenAdi": "ATATEPE SANAYİ SİTESİ 36. (Sokak)",
        "adi": "ATATEPE SANAYİ SİTESİ 36.",
        "kimlikNo": 898265
    },
    {
        "mahalleKayitNo": 147079,
        "turKod": 4,
        "bilesenAdi": "ATATEPE SANAYİ SİTESİ 37. (Sokak)",
        "adi": "ATATEPE SANAYİ SİTESİ 37.",
        "kimlikNo": 898266
    },
    {
        "mahalleKayitNo": 147079,
        "turKod": 3,
        "bilesenAdi": "ATATEPE SANAYİ SİTESİ 38. (Cadde)",
        "adi": "ATATEPE SANAYİ SİTESİ 38.",
        "kimlikNo": 898267
    },
    {
        "mahalleKayitNo": 147079,
        "turKod": 4,
        "bilesenAdi": "ATATEPE SANAYİ SİTESİ 39. (Sokak)",
        "adi": "ATATEPE SANAYİ SİTESİ 39.",
        "kimlikNo": 898268
    },
    {
        "mahalleKayitNo": 147079,
        "turKod": 4,
        "bilesenAdi": "ATATEPE SANAYİ SİTESİ 4. (Sokak)",
        "adi": "ATATEPE SANAYİ SİTESİ 4.",
        "kimlikNo": 897016
    },
    {
        "mahalleKayitNo": 147079,
        "turKod": 4,
        "bilesenAdi": "ATATEPE SANAYİ SİTESİ 40. (Sokak)",
        "adi": "ATATEPE SANAYİ SİTESİ 40.",
        "kimlikNo": 898269
    },
    {
        "mahalleKayitNo": 147079,
        "turKod": 4,
        "bilesenAdi": "ATATEPE SANAYİ SİTESİ 41. (Sokak)",
        "adi": "ATATEPE SANAYİ SİTESİ 41.",
        "kimlikNo": 898270
    },
    {
        "mahalleKayitNo": 147079,
        "turKod": 4,
        "bilesenAdi": "ATATEPE SANAYİ SİTESİ 42. (Sokak)",
        "adi": "ATATEPE SANAYİ SİTESİ 42.",
        "kimlikNo": 898271
    },
    {
        "mahalleKayitNo": 147079,
        "turKod": 4,
        "bilesenAdi": "ATATEPE SANAYİ SİTESİ 43. (Sokak)",
        "adi": "ATATEPE SANAYİ SİTESİ 43.",
        "kimlikNo": 898272
    },
    {
        "mahalleKayitNo": 147079,
        "turKod": 4,
        "bilesenAdi": "ATATEPE SANAYİ SİTESİ 44. (Sokak)",
        "adi": "ATATEPE SANAYİ SİTESİ 44.",
        "kimlikNo": 898273
    },
    {
        "mahalleKayitNo": 147079,
        "turKod": 4,
        "bilesenAdi": "ATATEPE SANAYİ SİTESİ 45. (Sokak)",
        "adi": "ATATEPE SANAYİ SİTESİ 45.",
        "kimlikNo": 898274
    },
    {
        "mahalleKayitNo": 147079,
        "turKod": 4,
        "bilesenAdi": "ATATEPE SANAYİ SİTESİ 46. (Sokak)",
        "adi": "ATATEPE SANAYİ SİTESİ 46.",
        "kimlikNo": 898275
    },
    {
        "mahalleKayitNo": 147079,
        "turKod": 4,
        "bilesenAdi": "ATATEPE SANAYİ SİTESİ 47. (Sokak)",
        "adi": "ATATEPE SANAYİ SİTESİ 47.",
        "kimlikNo": 898276
    },
    {
        "mahalleKayitNo": 147079,
        "turKod": 4,
        "bilesenAdi": "ATATEPE SANAYİ SİTESİ 48. (Sokak)",
        "adi": "ATATEPE SANAYİ SİTESİ 48.",
        "kimlikNo": 898277
    },
    {
        "mahalleKayitNo": 147079,
        "turKod": 4,
        "bilesenAdi": "ATATEPE SANAYİ SİTESİ 49. (Sokak)",
        "adi": "ATATEPE SANAYİ SİTESİ 49.",
        "kimlikNo": 898278
    },
    {
        "mahalleKayitNo": 147079,
        "turKod": 4,
        "bilesenAdi": "ATATEPE SANAYİ SİTESİ 5. (Sokak)",
        "adi": "ATATEPE SANAYİ SİTESİ 5.",
        "kimlikNo": 898241
    },
    {
        "mahalleKayitNo": 147079,
        "turKod": 4,
        "bilesenAdi": "ATATEPE SANAYİ SİTESİ 50. (Sokak)",
        "adi": "ATATEPE SANAYİ SİTESİ 50.",
        "kimlikNo": 897035
    },
    {
        "mahalleKayitNo": 147079,
        "turKod": 4,
        "bilesenAdi": "ATATEPE SANAYİ SİTESİ 51. (Sokak)",
        "adi": "ATATEPE SANAYİ SİTESİ 51.",
        "kimlikNo": 897036
    },
    {
        "mahalleKayitNo": 147079,
        "turKod": 4,
        "bilesenAdi": "ATATEPE SANAYİ SİTESİ 52. (Sokak)",
        "adi": "ATATEPE SANAYİ SİTESİ 52.",
        "kimlikNo": 898279
    },
    {
        "mahalleKayitNo": 147079,
        "turKod": 4,
        "bilesenAdi": "ATATEPE SANAYİ SİTESİ 53. (Sokak)",
        "adi": "ATATEPE SANAYİ SİTESİ 53.",
        "kimlikNo": 898280
    },
    {
        "mahalleKayitNo": 147079,
        "turKod": 4,
        "bilesenAdi": "ATATEPE SANAYİ SİTESİ 54. (Sokak)",
        "adi": "ATATEPE SANAYİ SİTESİ 54.",
        "kimlikNo": 898281
    },
    {
        "mahalleKayitNo": 147079,
        "turKod": 4,
        "bilesenAdi": "ATATEPE SANAYİ SİTESİ 55. (Sokak)",
        "adi": "ATATEPE SANAYİ SİTESİ 55.",
        "kimlikNo": 898282
    },
    {
        "mahalleKayitNo": 147079,
        "turKod": 4,
        "bilesenAdi": "ATATEPE SANAYİ SİTESİ 56. (Sokak)",
        "adi": "ATATEPE SANAYİ SİTESİ 56.",
        "kimlikNo": 898283
    },
    {
        "mahalleKayitNo": 147079,
        "turKod": 4,
        "bilesenAdi": "ATATEPE SANAYİ SİTESİ 57. (Sokak)",
        "adi": "ATATEPE SANAYİ SİTESİ 57.",
        "kimlikNo": 897037
    },
    {
        "mahalleKayitNo": 147079,
        "turKod": 4,
        "bilesenAdi": "ATATEPE SANAYİ SİTESİ 58. (Sokak)",
        "adi": "ATATEPE SANAYİ SİTESİ 58.",
        "kimlikNo": 898284
    },
    {
        "mahalleKayitNo": 147079,
        "turKod": 4,
        "bilesenAdi": "ATATEPE SANAYİ SİTESİ 59. (Sokak)",
        "adi": "ATATEPE SANAYİ SİTESİ 59.",
        "kimlikNo": 870216
    },
    {
        "mahalleKayitNo": 147079,
        "turKod": 4,
        "bilesenAdi": "ATATEPE SANAYİ SİTESİ 6. (Sokak)",
        "adi": "ATATEPE SANAYİ SİTESİ 6.",
        "kimlikNo": 822012
    },
    {
        "mahalleKayitNo": 147079,
        "turKod": 4,
        "bilesenAdi": "ATATEPE SANAYİ SİTESİ 60. (Sokak)",
        "adi": "ATATEPE SANAYİ SİTESİ 60.",
        "kimlikNo": 897038
    },
    {
        "mahalleKayitNo": 147079,
        "turKod": 4,
        "bilesenAdi": "ATATEPE SANAYİ SİTESİ 61. (Sokak)",
        "adi": "ATATEPE SANAYİ SİTESİ 61.",
        "kimlikNo": 898287
    },
    {
        "mahalleKayitNo": 147079,
        "turKod": 4,
        "bilesenAdi": "ATATEPE SANAYİ SİTESİ 62. (Sokak)",
        "adi": "ATATEPE SANAYİ SİTESİ 62.",
        "kimlikNo": 898288
    },
    {
        "mahalleKayitNo": 147079,
        "turKod": 4,
        "bilesenAdi": "ATATEPE SANAYİ SİTESİ 63. (Sokak)",
        "adi": "ATATEPE SANAYİ SİTESİ 63.",
        "kimlikNo": 898289
    },
    {
        "mahalleKayitNo": 147079,
        "turKod": 3,
        "bilesenAdi": "ATATEPE SANAYİ SİTESİ 64. (Cadde)",
        "adi": "ATATEPE SANAYİ SİTESİ 64.",
        "kimlikNo": 877716
    },
    {
        "mahalleKayitNo": 147079,
        "turKod": 4,
        "bilesenAdi": "ATATEPE SANAYİ SİTESİ 65. (Sokak)",
        "adi": "ATATEPE SANAYİ SİTESİ 65.",
        "kimlikNo": 898290
    },
    {
        "mahalleKayitNo": 147079,
        "turKod": 4,
        "bilesenAdi": "ATATEPE SANAYİ SİTESİ 66. (Sokak)",
        "adi": "ATATEPE SANAYİ SİTESİ 66.",
        "kimlikNo": 897039
    },
    {
        "mahalleKayitNo": 147079,
        "turKod": 4,
        "bilesenAdi": "ATATEPE SANAYİ SİTESİ 67. (Sokak)",
        "adi": "ATATEPE SANAYİ SİTESİ 67.",
        "kimlikNo": 897040
    },
    {
        "mahalleKayitNo": 147079,
        "turKod": 4,
        "bilesenAdi": "ATATEPE SANAYİ SİTESİ 68. (Sokak)",
        "adi": "ATATEPE SANAYİ SİTESİ 68.",
        "kimlikNo": 898292
    },
    {
        "mahalleKayitNo": 147079,
        "turKod": 4,
        "bilesenAdi": "ATATEPE SANAYİ SİTESİ 69. (Sokak)",
        "adi": "ATATEPE SANAYİ SİTESİ 69.",
        "kimlikNo": 897042
    },
    {
        "mahalleKayitNo": 147079,
        "turKod": 4,
        "bilesenAdi": "ATATEPE SANAYİ SİTESİ 7. (Sokak)",
        "adi": "ATATEPE SANAYİ SİTESİ 7.",
        "kimlikNo": 898242
    },
    {
        "mahalleKayitNo": 147079,
        "turKod": 4,
        "bilesenAdi": "ATATEPE SANAYİ SİTESİ 70. (Sokak)",
        "adi": "ATATEPE SANAYİ SİTESİ 70.",
        "kimlikNo": 898293
    },
    {
        "mahalleKayitNo": 147079,
        "turKod": 4,
        "bilesenAdi": "ATATEPE SANAYİ SİTESİ 71. (Sokak)",
        "adi": "ATATEPE SANAYİ SİTESİ 71.",
        "kimlikNo": 897043
    },
    {
        "mahalleKayitNo": 147079,
        "turKod": 4,
        "bilesenAdi": "ATATEPE SANAYİ SİTESİ 72. (Sokak)",
        "adi": "ATATEPE SANAYİ SİTESİ 72.",
        "kimlikNo": 897044
    },
    {
        "mahalleKayitNo": 147079,
        "turKod": 4,
        "bilesenAdi": "ATATEPE SANAYİ SİTESİ 73. (Sokak)",
        "adi": "ATATEPE SANAYİ SİTESİ 73.",
        "kimlikNo": 897045
    },
    {
        "mahalleKayitNo": 147079,
        "turKod": 4,
        "bilesenAdi": "ATATEPE SANAYİ SİTESİ 74. (Sokak)",
        "adi": "ATATEPE SANAYİ SİTESİ 74.",
        "kimlikNo": 897046
    },
    {
        "mahalleKayitNo": 147079,
        "turKod": 4,
        "bilesenAdi": "ATATEPE SANAYİ SİTESİ 75. (Sokak)",
        "adi": "ATATEPE SANAYİ SİTESİ 75.",
        "kimlikNo": 898294
    },
    {
        "mahalleKayitNo": 147079,
        "turKod": 4,
        "bilesenAdi": "ATATEPE SANAYİ SİTESİ 76. (Sokak)",
        "adi": "ATATEPE SANAYİ SİTESİ 76.",
        "kimlikNo": 898295
    },
    {
        "mahalleKayitNo": 147079,
        "turKod": 4,
        "bilesenAdi": "ATATEPE SANAYİ SİTESİ 77. (Sokak)",
        "adi": "ATATEPE SANAYİ SİTESİ 77.",
        "kimlikNo": 898296
    },
    {
        "mahalleKayitNo": 147079,
        "turKod": 4,
        "bilesenAdi": "ATATEPE SANAYİ SİTESİ 78. (Sokak)",
        "adi": "ATATEPE SANAYİ SİTESİ 78.",
        "kimlikNo": 898297
    },
    {
        "mahalleKayitNo": 147079,
        "turKod": 4,
        "bilesenAdi": "ATATEPE SANAYİ SİTESİ 79. (Sokak)",
        "adi": "ATATEPE SANAYİ SİTESİ 79.",
        "kimlikNo": 897047
    },
    {
        "mahalleKayitNo": 147079,
        "turKod": 4,
        "bilesenAdi": "ATATEPE SANAYİ SİTESİ 8. (Sokak)",
        "adi": "ATATEPE SANAYİ SİTESİ 8.",
        "kimlikNo": 898243
    },
    {
        "mahalleKayitNo": 147079,
        "turKod": 4,
        "bilesenAdi": "ATATEPE SANAYİ SİTESİ 80. (Sokak)",
        "adi": "ATATEPE SANAYİ SİTESİ 80.",
        "kimlikNo": 897048
    },
    {
        "mahalleKayitNo": 147079,
        "turKod": 4,
        "bilesenAdi": "ATATEPE SANAYİ SİTESİ 81. (Sokak)",
        "adi": "ATATEPE SANAYİ SİTESİ 81.",
        "kimlikNo": 898298
    },
    {
        "mahalleKayitNo": 147079,
        "turKod": 4,
        "bilesenAdi": "ATATEPE SANAYİ SİTESİ 82. (Sokak)",
        "adi": "ATATEPE SANAYİ SİTESİ 82.",
        "kimlikNo": 897049
    },
    {
        "mahalleKayitNo": 147079,
        "turKod": 4,
        "bilesenAdi": "ATATEPE SANAYİ SİTESİ 83. (Sokak)",
        "adi": "ATATEPE SANAYİ SİTESİ 83.",
        "kimlikNo": 898299
    },
    {
        "mahalleKayitNo": 147079,
        "turKod": 4,
        "bilesenAdi": "ATATEPE SANAYİ SİTESİ 84. (Sokak)",
        "adi": "ATATEPE SANAYİ SİTESİ 84.",
        "kimlikNo": 898300
    },
    {
        "mahalleKayitNo": 147079,
        "turKod": 4,
        "bilesenAdi": "ATATEPE SANAYİ SİTESİ 9. (Sokak)",
        "adi": "ATATEPE SANAYİ SİTESİ 9.",
        "kimlikNo": 898244
    },
    {
        "mahalleKayitNo": 147079,
        "turKod": 4,
        "bilesenAdi": "ORTAMANDIRA (Sokak)",
        "adi": "ORTAMANDIRA",
        "kimlikNo": 265201
    },
    {
        "mahalleKayitNo": 147079,
        "turKod": 4,
        "bilesenAdi": "ORTAMANDIRA 1 (Sokak)",
        "adi": "ORTAMANDIRA 1",
        "kimlikNo": 764584540
    },
    {
        "mahalleKayitNo": 147079,
        "turKod": 4,
        "bilesenAdi": "ORTAMANDIRA 10 (Sokak)",
        "adi": "ORTAMANDIRA 10",
        "kimlikNo": 705547531
    },
    {
        "mahalleKayitNo": 147079,
        "turKod": 4,
        "bilesenAdi": "ORTAMANDIRA 11 (Sokak)",
        "adi": "ORTAMANDIRA 11",
        "kimlikNo": 500007100
    },
    {
        "mahalleKayitNo": 147079,
        "turKod": 4,
        "bilesenAdi": "ORTAMANDIRA 12 (Sokak)",
        "adi": "ORTAMANDIRA 12",
        "kimlikNo": 640526321
    },
    {
        "mahalleKayitNo": 147079,
        "turKod": 4,
        "bilesenAdi": "ORTAMANDIRA 13 (Sokak)",
        "adi": "ORTAMANDIRA 13",
        "kimlikNo": 962307920
    },
    {
        "mahalleKayitNo": 147079,
        "turKod": 4,
        "bilesenAdi": "ORTAMANDIRA 14 (Sokak)",
        "adi": "ORTAMANDIRA 14",
        "kimlikNo": 759125760
    },
    {
        "mahalleKayitNo": 147079,
        "turKod": 4,
        "bilesenAdi": "ORTAMANDIRA 15 (Sokak)",
        "adi": "ORTAMANDIRA 15",
        "kimlikNo": 799074811
    },
    {
        "mahalleKayitNo": 147079,
        "turKod": 4,
        "bilesenAdi": "ORTAMANDIRA 16 (Sokak)",
        "adi": "ORTAMANDIRA 16",
        "kimlikNo": 917623770
    },
    {
        "mahalleKayitNo": 147079,
        "turKod": 4,
        "bilesenAdi": "ORTAMANDIRA 17 (Sokak)",
        "adi": "ORTAMANDIRA 17",
        "kimlikNo": 601011930
    },
    {
        "mahalleKayitNo": 147079,
        "turKod": 4,
        "bilesenAdi": "ORTAMANDIRA 18 (Sokak)",
        "adi": "ORTAMANDIRA 18",
        "kimlikNo": 576457801
    },
    {
        "mahalleKayitNo": 147079,
        "turKod": 4,
        "bilesenAdi": "ORTAMANDIRA 19 (Sokak)",
        "adi": "ORTAMANDIRA 19",
        "kimlikNo": 756836800
    },
    {
        "mahalleKayitNo": 147079,
        "turKod": 3,
        "bilesenAdi": "ORTAMANDIRA 2 (Cadde)",
        "adi": "ORTAMANDIRA 2",
        "kimlikNo": 939258161
    },
    {
        "mahalleKayitNo": 147079,
        "turKod": 4,
        "bilesenAdi": "ORTAMANDIRA 20 (Sokak)",
        "adi": "ORTAMANDIRA 20",
        "kimlikNo": 607422931
    },
    {
        "mahalleKayitNo": 147079,
        "turKod": 4,
        "bilesenAdi": "ORTAMANDIRA 21 (Sokak)",
        "adi": "ORTAMANDIRA 21",
        "kimlikNo": 500678591
    },
    {
        "mahalleKayitNo": 147079,
        "turKod": 4,
        "bilesenAdi": "ORTAMANDIRA 22 (Sokak)",
        "adi": "ORTAMANDIRA 22",
        "kimlikNo": 787498500
    },
    {
        "mahalleKayitNo": 147079,
        "turKod": 4,
        "bilesenAdi": "ORTAMANDIRA 23 (Sokak)",
        "adi": "ORTAMANDIRA 23",
        "kimlikNo": 784871390
    },
    {
        "mahalleKayitNo": 147079,
        "turKod": 4,
        "bilesenAdi": "ORTAMANDIRA 24 (Sokak)",
        "adi": "ORTAMANDIRA 24",
        "kimlikNo": 470554880
    },
    {
        "mahalleKayitNo": 147079,
        "turKod": 4,
        "bilesenAdi": "ORTAMANDIRA 25 (Sokak)",
        "adi": "ORTAMANDIRA 25",
        "kimlikNo": 660462280
    },
    {
        "mahalleKayitNo": 147079,
        "turKod": 4,
        "bilesenAdi": "ORTAMANDIRA 26 (Sokak)",
        "adi": "ORTAMANDIRA 26",
        "kimlikNo": 537691470
    },
    {
        "mahalleKayitNo": 147079,
        "turKod": 4,
        "bilesenAdi": "ORTAMANDIRA 27 (Sokak)",
        "adi": "ORTAMANDIRA 27",
        "kimlikNo": 684450970
    },
    {
        "mahalleKayitNo": 147079,
        "turKod": 4,
        "bilesenAdi": "ORTAMANDIRA 28 (Sokak)",
        "adi": "ORTAMANDIRA 28",
        "kimlikNo": 517617571
    },
    {
        "mahalleKayitNo": 147079,
        "turKod": 4,
        "bilesenAdi": "ORTAMANDIRA 29 (Sokak)",
        "adi": "ORTAMANDIRA 29",
        "kimlikNo": 885535811
    },
    {
        "mahalleKayitNo": 147079,
        "turKod": 4,
        "bilesenAdi": "ORTAMANDIRA 3 (Sokak)",
        "adi": "ORTAMANDIRA 3",
        "kimlikNo": 507470620
    },
    {
        "mahalleKayitNo": 147079,
        "turKod": 4,
        "bilesenAdi": "ORTAMANDIRA 30 (Sokak)",
        "adi": "ORTAMANDIRA 30",
        "kimlikNo": 630772670
    },
    {
        "mahalleKayitNo": 147079,
        "turKod": 4,
        "bilesenAdi": "ORTAMANDIRA 31 (Sokak)",
        "adi": "ORTAMANDIRA 31",
        "kimlikNo": 714200950
    },
    {
        "mahalleKayitNo": 147079,
        "turKod": 4,
        "bilesenAdi": "ORTAMANDIRA 32 (Sokak)",
        "adi": "ORTAMANDIRA 32",
        "kimlikNo": 507039331
    },
    {
        "mahalleKayitNo": 147079,
        "turKod": 4,
        "bilesenAdi": "ORTAMANDIRA 33 (Sokak)",
        "adi": "ORTAMANDIRA 33",
        "kimlikNo": 984846861
    },
    {
        "mahalleKayitNo": 147079,
        "turKod": 4,
        "bilesenAdi": "ORTAMANDIRA 34 (Sokak)",
        "adi": "ORTAMANDIRA 34",
        "kimlikNo": 912253000
    },
    {
        "mahalleKayitNo": 147079,
        "turKod": 4,
        "bilesenAdi": "ORTAMANDIRA 35 (Sokak)",
        "adi": "ORTAMANDIRA 35",
        "kimlikNo": 761445261
    },
    {
        "mahalleKayitNo": 147079,
        "turKod": 4,
        "bilesenAdi": "ORTAMANDIRA 36 (Sokak)",
        "adi": "ORTAMANDIRA 36",
        "kimlikNo": 560495701
    },
    {
        "mahalleKayitNo": 147079,
        "turKod": 4,
        "bilesenAdi": "ORTAMANDIRA 37 (Sokak)",
        "adi": "ORTAMANDIRA 37",
        "kimlikNo": 753147401
    },
    {
        "mahalleKayitNo": 147079,
        "turKod": 4,
        "bilesenAdi": "ORTAMANDIRA 38 (Sokak)",
        "adi": "ORTAMANDIRA 38",
        "kimlikNo": 734937360
    },
    {
        "mahalleKayitNo": 147079,
        "turKod": 4,
        "bilesenAdi": "ORTAMANDIRA 39 (Sokak)",
        "adi": "ORTAMANDIRA 39",
        "kimlikNo": 539353591
    },
    {
        "mahalleKayitNo": 147079,
        "turKod": 4,
        "bilesenAdi": "ORTAMANDIRA 4 (Sokak)",
        "adi": "ORTAMANDIRA 4",
        "kimlikNo": 493876730
    },
    {
        "mahalleKayitNo": 147079,
        "turKod": 4,
        "bilesenAdi": "ORTAMANDIRA 40 (Sokak)",
        "adi": "ORTAMANDIRA 40",
        "kimlikNo": 601682831
    },
    {
        "mahalleKayitNo": 147079,
        "turKod": 4,
        "bilesenAdi": "ORTAMANDIRA 41 (Sokak)",
        "adi": "ORTAMANDIRA 41",
        "kimlikNo": 821649890
    },
    {
        "mahalleKayitNo": 147079,
        "turKod": 4,
        "bilesenAdi": "ORTAMANDIRA 42 (Sokak)",
        "adi": "ORTAMANDIRA 42",
        "kimlikNo": 466069500
    },
    {
        "mahalleKayitNo": 147079,
        "turKod": 4,
        "bilesenAdi": "ORTAMANDIRA 43 (Sokak)",
        "adi": "ORTAMANDIRA 43",
        "kimlikNo": 833273871
    },
    {
        "mahalleKayitNo": 147079,
        "turKod": 4,
        "bilesenAdi": "ORTAMANDIRA 44 (Sokak)",
        "adi": "ORTAMANDIRA 44",
        "kimlikNo": 815763651
    },
    {
        "mahalleKayitNo": 147079,
        "turKod": 4,
        "bilesenAdi": "ORTAMANDIRA 45 (Sokak)",
        "adi": "ORTAMANDIRA 45",
        "kimlikNo": 841856360
    },
    {
        "mahalleKayitNo": 147079,
        "turKod": 4,
        "bilesenAdi": "ORTAMANDIRA 46 (Sokak)",
        "adi": "ORTAMANDIRA 46",
        "kimlikNo": 915174580
    },
    {
        "mahalleKayitNo": 147079,
        "turKod": 4,
        "bilesenAdi": "ORTAMANDIRA 47 (Sokak)",
        "adi": "ORTAMANDIRA 47",
        "kimlikNo": 858724140
    },
    {
        "mahalleKayitNo": 147079,
        "turKod": 4,
        "bilesenAdi": "ORTAMANDIRA 48 (Sokak)",
        "adi": "ORTAMANDIRA 48",
        "kimlikNo": 769128981
    },
    {
        "mahalleKayitNo": 147079,
        "turKod": 4,
        "bilesenAdi": "ORTAMANDIRA 49 (Sokak)",
        "adi": "ORTAMANDIRA 49",
        "kimlikNo": 854848551
    },
    {
        "mahalleKayitNo": 147079,
        "turKod": 4,
        "bilesenAdi": "ORTAMANDIRA 5 (Sokak)",
        "adi": "ORTAMANDIRA 5",
        "kimlikNo": 625307611
    },
    {
        "mahalleKayitNo": 147079,
        "turKod": 4,
        "bilesenAdi": "ORTAMANDIRA 50 (Sokak)",
        "adi": "ORTAMANDIRA 50",
        "kimlikNo": 735072040
    },
    {
        "mahalleKayitNo": 147079,
        "turKod": 4,
        "bilesenAdi": "ORTAMANDIRA 51 (Sokak)",
        "adi": "ORTAMANDIRA 51",
        "kimlikNo": 995157440
    },
    {
        "mahalleKayitNo": 147079,
        "turKod": 4,
        "bilesenAdi": "ORTAMANDIRA 52 (Sokak)",
        "adi": "ORTAMANDIRA 52",
        "kimlikNo": 993617350
    },
    {
        "mahalleKayitNo": 147079,
        "turKod": 4,
        "bilesenAdi": "ORTAMANDIRA 53 (Sokak)",
        "adi": "ORTAMANDIRA 53",
        "kimlikNo": 672454720
    },
    {
        "mahalleKayitNo": 147079,
        "turKod": 4,
        "bilesenAdi": "ORTAMANDIRA 54 (Sokak)",
        "adi": "ORTAMANDIRA 54",
        "kimlikNo": 577045790
    },
    {
        "mahalleKayitNo": 147079,
        "turKod": 4,
        "bilesenAdi": "ORTAMANDIRA 55 (Sokak)",
        "adi": "ORTAMANDIRA 55",
        "kimlikNo": 990406361
    },
    {
        "mahalleKayitNo": 147079,
        "turKod": 4,
        "bilesenAdi": "ORTAMANDIRA 56 (Sokak)",
        "adi": "ORTAMANDIRA 56",
        "kimlikNo": 539085131
    },
    {
        "mahalleKayitNo": 147079,
        "turKod": 4,
        "bilesenAdi": "ORTAMANDIRA 57 (Sokak)",
        "adi": "ORTAMANDIRA 57",
        "kimlikNo": 724106080
    },
    {
        "mahalleKayitNo": 147079,
        "turKod": 4,
        "bilesenAdi": "ORTAMANDIRA 58 (Sokak)",
        "adi": "ORTAMANDIRA 58",
        "kimlikNo": 744499761
    },
    {
        "mahalleKayitNo": 147079,
        "turKod": 4,
        "bilesenAdi": "ORTAMANDIRA 59 (Sokak)",
        "adi": "ORTAMANDIRA 59",
        "kimlikNo": 949300051
    },
    {
        "mahalleKayitNo": 147079,
        "turKod": 4,
        "bilesenAdi": "ORTAMANDIRA 6 (Sokak)",
        "adi": "ORTAMANDIRA 6",
        "kimlikNo": 628120860
    },
    {
        "mahalleKayitNo": 147079,
        "turKod": 4,
        "bilesenAdi": "ORTAMANDIRA 60 (Sokak)",
        "adi": "ORTAMANDIRA 60",
        "kimlikNo": 613900500
    },
    {
        "mahalleKayitNo": 147079,
        "turKod": 4,
        "bilesenAdi": "ORTAMANDIRA 7 (Sokak)",
        "adi": "ORTAMANDIRA 7",
        "kimlikNo": 748291510
    },
    {
        "mahalleKayitNo": 147079,
        "turKod": 4,
        "bilesenAdi": "ORTAMANDIRA 8 (Sokak)",
        "adi": "ORTAMANDIRA 8",
        "kimlikNo": 790847861
    },
    {
        "mahalleKayitNo": 147079,
        "turKod": 4,
        "bilesenAdi": "ORTAMANDIRA 9 (Sokak)",
        "adi": "ORTAMANDIRA 9",
        "kimlikNo": 789198911
    }
]