[
    {
        "mahalleKayitNo": 147307,
        "turKod": 4,
        "bilesenAdi": "19001 (Sokak)",
        "adi": "19001",
        "kimlikNo": 107645610
    },
    {
        "mahalleKayitNo": 147307,
        "turKod": 4,
        "bilesenAdi": "19014 (Sokak)",
        "adi": "19014",
        "kimlikNo": 781424521
    },
    {
        "mahalleKayitNo": 147307,
        "turKod": 4,
        "bilesenAdi": "19015 (Sokak)",
        "adi": "19015",
        "kimlikNo": 852818481
    },
    {
        "mahalleKayitNo": 147307,
        "turKod": 4,
        "bilesenAdi": "19016 (Sokak)",
        "adi": "19016",
        "kimlikNo": 195026401
    },
    {
        "mahalleKayitNo": 147307,
        "turKod": 4,
        "bilesenAdi": "19017 (Sokak)",
        "adi": "19017",
        "kimlikNo": 789152951
    },
    {
        "mahalleKayitNo": 147307,
        "turKod": 4,
        "bilesenAdi": "19018 (Sokak)",
        "adi": "19018",
        "kimlikNo": 573396241
    },
    {
        "mahalleKayitNo": 147307,
        "turKod": 4,
        "bilesenAdi": "19019 (Sokak)",
        "adi": "19019",
        "kimlikNo": 755798621
    },
    {
        "mahalleKayitNo": 147307,
        "turKod": 4,
        "bilesenAdi": "19024 (Sokak)",
        "adi": "19024",
        "kimlikNo": 705386991
    },
    {
        "mahalleKayitNo": 147307,
        "turKod": 4,
        "bilesenAdi": "ÇAYÜSTÜ (Sokak)",
        "adi": "ÇAYÜSTÜ",
        "kimlikNo": 341074
    },
    {
        "mahalleKayitNo": 147307,
        "turKod": 4,
        "bilesenAdi": "ÇAYÜSTÜ10 (Sokak)",
        "adi": "ÇAYÜSTÜ10",
        "kimlikNo": 371908650
    },
    {
        "mahalleKayitNo": 147307,
        "turKod": 4,
        "bilesenAdi": "ÇAYÜSTÜ11 (Sokak)",
        "adi": "ÇAYÜSTÜ11",
        "kimlikNo": 157243130
    },
    {
        "mahalleKayitNo": 147307,
        "turKod": 4,
        "bilesenAdi": "ÇAYÜSTÜ12 (Sokak)",
        "adi": "ÇAYÜSTÜ12",
        "kimlikNo": 878531490
    },
    {
        "mahalleKayitNo": 147307,
        "turKod": 4,
        "bilesenAdi": "ÇAYÜSTÜ13 (Sokak)",
        "adi": "ÇAYÜSTÜ13",
        "kimlikNo": 999398941
    },
    {
        "mahalleKayitNo": 147307,
        "turKod": 4,
        "bilesenAdi": "ÇAYÜSTÜ14 (Sokak)",
        "adi": "ÇAYÜSTÜ14",
        "kimlikNo": 460958571
    },
    {
        "mahalleKayitNo": 147307,
        "turKod": 4,
        "bilesenAdi": "ÇAYÜSTÜ15 (Sokak)",
        "adi": "ÇAYÜSTÜ15",
        "kimlikNo": 483828081
    },
    {
        "mahalleKayitNo": 147307,
        "turKod": 4,
        "bilesenAdi": "ÇAYÜSTÜ2 (Sokak)",
        "adi": "ÇAYÜSTÜ2",
        "kimlikNo": 408963340
    },
    {
        "mahalleKayitNo": 147307,
        "turKod": 4,
        "bilesenAdi": "ÇAYÜSTÜ3 (Sokak)",
        "adi": "ÇAYÜSTÜ3",
        "kimlikNo": 949764120
    },
    {
        "mahalleKayitNo": 147307,
        "turKod": 4,
        "bilesenAdi": "ÇAYÜSTÜ4 (Sokak)",
        "adi": "ÇAYÜSTÜ4",
        "kimlikNo": 592779470
    },
    {
        "mahalleKayitNo": 147307,
        "turKod": 4,
        "bilesenAdi": "ÇAYÜSTÜ5 (Sokak)",
        "adi": "ÇAYÜSTÜ5",
        "kimlikNo": 222568380
    },
    {
        "mahalleKayitNo": 147307,
        "turKod": 4,
        "bilesenAdi": "ÇAYÜSTÜ6 (Sokak)",
        "adi": "ÇAYÜSTÜ6",
        "kimlikNo": 805990610
    },
    {
        "mahalleKayitNo": 147307,
        "turKod": 4,
        "bilesenAdi": "ÇAYÜSTÜ7 (Sokak)",
        "adi": "ÇAYÜSTÜ7",
        "kimlikNo": 160011900
    },
    {
        "mahalleKayitNo": 147307,
        "turKod": 4,
        "bilesenAdi": "ÇAYÜSTÜ8 (Sokak)",
        "adi": "ÇAYÜSTÜ8",
        "kimlikNo": 129948770
    },
    {
        "mahalleKayitNo": 147307,
        "turKod": 4,
        "bilesenAdi": "ÇAYÜSTÜ9 (Sokak)",
        "adi": "ÇAYÜSTÜ9",
        "kimlikNo": 191599870
    }
]