[
    {
        "mahalleKayitNo": 148045,
        "turKod": 4,
        "bilesenAdi": "BOZÖREN (Sokak)",
        "adi": "BOZÖREN",
        "kimlikNo": 553742
    },
    {
        "mahalleKayitNo": 148045,
        "turKod": 4,
        "bilesenAdi": "BOZÖREN 1 (Sokak)",
        "adi": "BOZÖREN 1",
        "kimlikNo": 626613350
    },
    {
        "mahalleKayitNo": 148045,
        "turKod": 4,
        "bilesenAdi": "BOZÖREN 10 (Sokak)",
        "adi": "BOZÖREN 10",
        "kimlikNo": 948226160
    },
    {
        "mahalleKayitNo": 148045,
        "turKod": 4,
        "bilesenAdi": "BOZÖREN 11 (Sokak)",
        "adi": "BOZÖREN 11",
        "kimlikNo": 805807151
    },
    {
        "mahalleKayitNo": 148045,
        "turKod": 4,
        "bilesenAdi": "BOZÖREN 12 (Sokak)",
        "adi": "BOZÖREN 12",
        "kimlikNo": 484209130
    },
    {
        "mahalleKayitNo": 148045,
        "turKod": 4,
        "bilesenAdi": "BOZÖREN 13 (Sokak)",
        "adi": "BOZÖREN 13",
        "kimlikNo": 793088051
    },
    {
        "mahalleKayitNo": 148045,
        "turKod": 4,
        "bilesenAdi": "BOZÖREN 14 (Sokak)",
        "adi": "BOZÖREN 14",
        "kimlikNo": 597869391
    },
    {
        "mahalleKayitNo": 148045,
        "turKod": 4,
        "bilesenAdi": "BOZÖREN 15 (Sokak)",
        "adi": "BOZÖREN 15",
        "kimlikNo": 815919010
    },
    {
        "mahalleKayitNo": 148045,
        "turKod": 4,
        "bilesenAdi": "BOZÖREN 16 (Sokak)",
        "adi": "BOZÖREN 16",
        "kimlikNo": 603245631
    },
    {
        "mahalleKayitNo": 148045,
        "turKod": 4,
        "bilesenAdi": "BOZÖREN 17 (Sokak)",
        "adi": "BOZÖREN 17",
        "kimlikNo": 774239940
    },
    {
        "mahalleKayitNo": 148045,
        "turKod": 4,
        "bilesenAdi": "BOZÖREN 18 (Sokak)",
        "adi": "BOZÖREN 18",
        "kimlikNo": 669501711
    },
    {
        "mahalleKayitNo": 148045,
        "turKod": 4,
        "bilesenAdi": "BOZÖREN 19 (Sokak)",
        "adi": "BOZÖREN 19",
        "kimlikNo": 527536881
    },
    {
        "mahalleKayitNo": 148045,
        "turKod": 4,
        "bilesenAdi": "BOZÖREN 2 (Sokak)",
        "adi": "BOZÖREN 2",
        "kimlikNo": 888104111
    },
    {
        "mahalleKayitNo": 148045,
        "turKod": 4,
        "bilesenAdi": "BOZÖREN 20 (Sokak)",
        "adi": "BOZÖREN 20",
        "kimlikNo": 767261731
    },
    {
        "mahalleKayitNo": 148045,
        "turKod": 4,
        "bilesenAdi": "BOZÖREN 21 (Sokak)",
        "adi": "BOZÖREN 21",
        "kimlikNo": 491257271
    },
    {
        "mahalleKayitNo": 148045,
        "turKod": 4,
        "bilesenAdi": "BOZÖREN 22 (Sokak)",
        "adi": "BOZÖREN 22",
        "kimlikNo": 734434911
    },
    {
        "mahalleKayitNo": 148045,
        "turKod": 4,
        "bilesenAdi": "BOZÖREN 23 (Sokak)",
        "adi": "BOZÖREN 23",
        "kimlikNo": 684228311
    },
    {
        "mahalleKayitNo": 148045,
        "turKod": 4,
        "bilesenAdi": "BOZÖREN 24 (Sokak)",
        "adi": "BOZÖREN 24",
        "kimlikNo": 461034040
    },
    {
        "mahalleKayitNo": 148045,
        "turKod": 4,
        "bilesenAdi": "BOZÖREN 25 (Sokak)",
        "adi": "BOZÖREN 25",
        "kimlikNo": 907963921
    },
    {
        "mahalleKayitNo": 148045,
        "turKod": 4,
        "bilesenAdi": "BOZÖREN 26 (Sokak)",
        "adi": "BOZÖREN 26",
        "kimlikNo": 834338391
    },
    {
        "mahalleKayitNo": 148045,
        "turKod": 4,
        "bilesenAdi": "BOZÖREN 27 (Sokak)",
        "adi": "BOZÖREN 27",
        "kimlikNo": 899226521
    },
    {
        "mahalleKayitNo": 148045,
        "turKod": 4,
        "bilesenAdi": "BOZÖREN 28 (Sokak)",
        "adi": "BOZÖREN 28",
        "kimlikNo": 677576251
    },
    {
        "mahalleKayitNo": 148045,
        "turKod": 4,
        "bilesenAdi": "BOZÖREN 29 (Sokak)",
        "adi": "BOZÖREN 29",
        "kimlikNo": 667708190
    },
    {
        "mahalleKayitNo": 148045,
        "turKod": 4,
        "bilesenAdi": "BOZÖREN 3 (Sokak)",
        "adi": "BOZÖREN 3",
        "kimlikNo": 503678201
    },
    {
        "mahalleKayitNo": 148045,
        "turKod": 4,
        "bilesenAdi": "BOZÖREN 30 (Sokak)",
        "adi": "BOZÖREN 30",
        "kimlikNo": 873638751
    },
    {
        "mahalleKayitNo": 148045,
        "turKod": 4,
        "bilesenAdi": "BOZÖREN 31 (Sokak)",
        "adi": "BOZÖREN 31",
        "kimlikNo": 881785120
    },
    {
        "mahalleKayitNo": 148045,
        "turKod": 4,
        "bilesenAdi": "BOZÖREN 32 (Sokak)",
        "adi": "BOZÖREN 32",
        "kimlikNo": 576867500
    },
    {
        "mahalleKayitNo": 148045,
        "turKod": 4,
        "bilesenAdi": "BOZÖREN 33 (Sokak)",
        "adi": "BOZÖREN 33",
        "kimlikNo": 465828051
    },
    {
        "mahalleKayitNo": 148045,
        "turKod": 4,
        "bilesenAdi": "BOZÖREN 34 (Sokak)",
        "adi": "BOZÖREN 34",
        "kimlikNo": 465472121
    },
    {
        "mahalleKayitNo": 148045,
        "turKod": 4,
        "bilesenAdi": "BOZÖREN 35 (Sokak)",
        "adi": "BOZÖREN 35",
        "kimlikNo": 714610081
    },
    {
        "mahalleKayitNo": 148045,
        "turKod": 4,
        "bilesenAdi": "BOZÖREN 36 (Sokak)",
        "adi": "BOZÖREN 36",
        "kimlikNo": 510156910
    },
    {
        "mahalleKayitNo": 148045,
        "turKod": 4,
        "bilesenAdi": "BOZÖREN 37 (Sokak)",
        "adi": "BOZÖREN 37",
        "kimlikNo": 74343856
    },
    {
        "mahalleKayitNo": 148045,
        "turKod": 4,
        "bilesenAdi": "BOZÖREN 38 (Sokak)",
        "adi": "BOZÖREN 38",
        "kimlikNo": 797382170
    },
    {
        "mahalleKayitNo": 148045,
        "turKod": 4,
        "bilesenAdi": "BOZÖREN 39 (Sokak)",
        "adi": "BOZÖREN 39",
        "kimlikNo": 873781701
    },
    {
        "mahalleKayitNo": 148045,
        "turKod": 4,
        "bilesenAdi": "BOZÖREN 4 (Sokak)",
        "adi": "BOZÖREN 4",
        "kimlikNo": 67443960
    },
    {
        "mahalleKayitNo": 148045,
        "turKod": 4,
        "bilesenAdi": "BOZÖREN 40 (Sokak)",
        "adi": "BOZÖREN 40",
        "kimlikNo": 623056441
    },
    {
        "mahalleKayitNo": 148045,
        "turKod": 4,
        "bilesenAdi": "BOZÖREN 41 (Sokak)",
        "adi": "BOZÖREN 41",
        "kimlikNo": 964836561
    },
    {
        "mahalleKayitNo": 148045,
        "turKod": 4,
        "bilesenAdi": "BOZÖREN 42 (Sokak)",
        "adi": "BOZÖREN 42",
        "kimlikNo": 509446280
    },
    {
        "mahalleKayitNo": 148045,
        "turKod": 4,
        "bilesenAdi": "BOZÖREN 43 (Sokak)",
        "adi": "BOZÖREN 43",
        "kimlikNo": 939709521
    },
    {
        "mahalleKayitNo": 148045,
        "turKod": 4,
        "bilesenAdi": "BOZÖREN 44 (Sokak)",
        "adi": "BOZÖREN 44",
        "kimlikNo": 679605180
    },
    {
        "mahalleKayitNo": 148045,
        "turKod": 4,
        "bilesenAdi": "BOZÖREN 45 (Sokak)",
        "adi": "BOZÖREN 45",
        "kimlikNo": 565728290
    },
    {
        "mahalleKayitNo": 148045,
        "turKod": 4,
        "bilesenAdi": "BOZÖREN 46 (Sokak)",
        "adi": "BOZÖREN 46",
        "kimlikNo": 840600520
    },
    {
        "mahalleKayitNo": 148045,
        "turKod": 4,
        "bilesenAdi": "BOZÖREN 47 (Sokak)",
        "adi": "BOZÖREN 47",
        "kimlikNo": 10098721
    },
    {
        "mahalleKayitNo": 148045,
        "turKod": 4,
        "bilesenAdi": "BOZÖREN 48 (Sokak)",
        "adi": "BOZÖREN 48",
        "kimlikNo": 881661521
    },
    {
        "mahalleKayitNo": 148045,
        "turKod": 4,
        "bilesenAdi": "BOZÖREN 49 (Sokak)",
        "adi": "BOZÖREN 49",
        "kimlikNo": 960104911
    },
    {
        "mahalleKayitNo": 148045,
        "turKod": 4,
        "bilesenAdi": "BOZÖREN 5 (Sokak)",
        "adi": "BOZÖREN 5",
        "kimlikNo": 876268001
    },
    {
        "mahalleKayitNo": 148045,
        "turKod": 4,
        "bilesenAdi": "BOZÖREN 50 (Sokak)",
        "adi": "BOZÖREN 50",
        "kimlikNo": 508587601
    },
    {
        "mahalleKayitNo": 148045,
        "turKod": 4,
        "bilesenAdi": "BOZÖREN 51 (Sokak)",
        "adi": "BOZÖREN 51",
        "kimlikNo": 460980910
    },
    {
        "mahalleKayitNo": 148045,
        "turKod": 4,
        "bilesenAdi": "BOZÖREN 52 (Sokak)",
        "adi": "BOZÖREN 52",
        "kimlikNo": 946555780
    },
    {
        "mahalleKayitNo": 148045,
        "turKod": 4,
        "bilesenAdi": "BOZÖREN 53 (Sokak)",
        "adi": "BOZÖREN 53",
        "kimlikNo": 626659480
    },
    {
        "mahalleKayitNo": 148045,
        "turKod": 4,
        "bilesenAdi": "BOZÖREN 54 (Sokak)",
        "adi": "BOZÖREN 54",
        "kimlikNo": 459043310
    },
    {
        "mahalleKayitNo": 148045,
        "turKod": 4,
        "bilesenAdi": "BOZÖREN 55 (Sokak)",
        "adi": "BOZÖREN 55",
        "kimlikNo": 531697691
    },
    {
        "mahalleKayitNo": 148045,
        "turKod": 4,
        "bilesenAdi": "BOZÖREN 56 (Sokak)",
        "adi": "BOZÖREN 56",
        "kimlikNo": 785429171
    },
    {
        "mahalleKayitNo": 148045,
        "turKod": 4,
        "bilesenAdi": "BOZÖREN 57 (Sokak)",
        "adi": "BOZÖREN 57",
        "kimlikNo": 990384161
    },
    {
        "mahalleKayitNo": 148045,
        "turKod": 4,
        "bilesenAdi": "BOZÖREN 58 (Sokak)",
        "adi": "BOZÖREN 58",
        "kimlikNo": 667361821
    },
    {
        "mahalleKayitNo": 148045,
        "turKod": 4,
        "bilesenAdi": "BOZÖREN 59 (Sokak)",
        "adi": "BOZÖREN 59",
        "kimlikNo": 447730751
    },
    {
        "mahalleKayitNo": 148045,
        "turKod": 4,
        "bilesenAdi": "BOZÖREN 6 (Sokak)",
        "adi": "BOZÖREN 6",
        "kimlikNo": 908254800
    },
    {
        "mahalleKayitNo": 148045,
        "turKod": 4,
        "bilesenAdi": "BOZÖREN 60 (Sokak)",
        "adi": "BOZÖREN 60",
        "kimlikNo": 168064811
    },
    {
        "mahalleKayitNo": 148045,
        "turKod": 4,
        "bilesenAdi": "BOZÖREN 61 (Sokak)",
        "adi": "BOZÖREN 61",
        "kimlikNo": 79867511
    },
    {
        "mahalleKayitNo": 148045,
        "turKod": 4,
        "bilesenAdi": "BOZÖREN 62 (Sokak)",
        "adi": "BOZÖREN 62",
        "kimlikNo": 463242571
    },
    {
        "mahalleKayitNo": 148045,
        "turKod": 4,
        "bilesenAdi": "BOZÖREN 63 (Sokak)",
        "adi": "BOZÖREN 63",
        "kimlikNo": 107857491
    },
    {
        "mahalleKayitNo": 148045,
        "turKod": 4,
        "bilesenAdi": "BOZÖREN 64 (Sokak)",
        "adi": "BOZÖREN 64",
        "kimlikNo": 877003081
    },
    {
        "mahalleKayitNo": 148045,
        "turKod": 4,
        "bilesenAdi": "BOZÖREN 65 (Sokak)",
        "adi": "BOZÖREN 65",
        "kimlikNo": 36363430
    },
    {
        "mahalleKayitNo": 148045,
        "turKod": 4,
        "bilesenAdi": "BOZÖREN 66 (Sokak)",
        "adi": "BOZÖREN 66",
        "kimlikNo": 29267119
    },
    {
        "mahalleKayitNo": 148045,
        "turKod": 4,
        "bilesenAdi": "BOZÖREN 67 (Sokak)",
        "adi": "BOZÖREN 67",
        "kimlikNo": 35736354
    },
    {
        "mahalleKayitNo": 148045,
        "turKod": 4,
        "bilesenAdi": "BOZÖREN 68 (Sokak)",
        "adi": "BOZÖREN 68",
        "kimlikNo": 774957371
    },
    {
        "mahalleKayitNo": 148045,
        "turKod": 4,
        "bilesenAdi": "BOZÖREN 69 (Sokak)",
        "adi": "BOZÖREN 69",
        "kimlikNo": 23020308
    },
    {
        "mahalleKayitNo": 148045,
        "turKod": 4,
        "bilesenAdi": "BOZÖREN 7 (Sokak)",
        "adi": "BOZÖREN 7",
        "kimlikNo": 754403050
    },
    {
        "mahalleKayitNo": 148045,
        "turKod": 4,
        "bilesenAdi": "BOZÖREN 70 (Sokak)",
        "adi": "BOZÖREN 70",
        "kimlikNo": 58932211
    },
    {
        "mahalleKayitNo": 148045,
        "turKod": 4,
        "bilesenAdi": "BOZÖREN 71 (Sokak)",
        "adi": "BOZÖREN 71",
        "kimlikNo": 78036605
    },
    {
        "mahalleKayitNo": 148045,
        "turKod": 4,
        "bilesenAdi": "BOZÖREN 72 (Sokak)",
        "adi": "BOZÖREN 72",
        "kimlikNo": 337012511
    },
    {
        "mahalleKayitNo": 148045,
        "turKod": 4,
        "bilesenAdi": "BOZÖREN 73 (Sokak)",
        "adi": "BOZÖREN 73",
        "kimlikNo": 78397700
    },
    {
        "mahalleKayitNo": 148045,
        "turKod": 4,
        "bilesenAdi": "BOZÖREN 74 (Sokak)",
        "adi": "BOZÖREN 74",
        "kimlikNo": 46434585
    },
    {
        "mahalleKayitNo": 148045,
        "turKod": 4,
        "bilesenAdi": "BOZÖREN 8 (Sokak)",
        "adi": "BOZÖREN 8",
        "kimlikNo": 658698691
    },
    {
        "mahalleKayitNo": 148045,
        "turKod": 4,
        "bilesenAdi": "BOZÖREN 9 (Sokak)",
        "adi": "BOZÖREN 9",
        "kimlikNo": 753198710
    },
    {
        "mahalleKayitNo": 148045,
        "turKod": 4,
        "bilesenAdi": "BOZÖREN/37 (Sokak)",
        "adi": "BOZÖREN/37",
        "kimlikNo": 738587551
    },
    {
        "mahalleKayitNo": 148045,
        "turKod": 4,
        "bilesenAdi": "BOZÖREN/47 (Sokak)",
        "adi": "BOZÖREN/47",
        "kimlikNo": 729132961
    },
    {
        "mahalleKayitNo": 148045,
        "turKod": 4,
        "bilesenAdi": "BOZÖREN/57 (Sokak)",
        "adi": "BOZÖREN/57",
        "kimlikNo": 158299301
    }
]