[
    {
        "mahalleKayitNo": 159749,
        "turKod": 4,
        "bilesenAdi": "ALİKÖSELER (Sokak)",
        "adi": "ALİKÖSELER",
        "kimlikNo": 351316
    },
    {
        "mahalleKayitNo": 159749,
        "turKod": 5,
        "bilesenAdi": "ÇAY (Küme Evler)",
        "adi": "ÇAY",
        "kimlikNo": 606695
    },
    {
        "mahalleKayitNo": 159749,
        "turKod": 5,
        "bilesenAdi": "DERE (Küme Evler)",
        "adi": "DERE",
        "kimlikNo": 599597
    },
    {
        "mahalleKayitNo": 159749,
        "turKod": 4,
        "bilesenAdi": "GÜLLÜYURT (Sokak)",
        "adi": "GÜLLÜYURT",
        "kimlikNo": 606230
    },
    {
        "mahalleKayitNo": 159749,
        "turKod": 5,
        "bilesenAdi": "HAYDARLAR (Küme Evler)",
        "adi": "HAYDARLAR",
        "kimlikNo": 609642
    },
    {
        "mahalleKayitNo": 159749,
        "turKod": 5,
        "bilesenAdi": "İDRİSLER (Küme Evler)",
        "adi": "İDRİSLER",
        "kimlikNo": 605769
    },
    {
        "mahalleKayitNo": 159749,
        "turKod": 5,
        "bilesenAdi": "KAHVECİLER (Küme Evler)",
        "adi": "KAHVECİLER",
        "kimlikNo": 610422
    },
    {
        "mahalleKayitNo": 159749,
        "turKod": 5,
        "bilesenAdi": "KARALİL (Küme Evler)",
        "adi": "KARALİL",
        "kimlikNo": 604316
    },
    {
        "mahalleKayitNo": 159749,
        "turKod": 5,
        "bilesenAdi": "KÖSELER (Küme Evler)",
        "adi": "KÖSELER",
        "kimlikNo": 600011
    },
    {
        "mahalleKayitNo": 159749,
        "turKod": 5,
        "bilesenAdi": "TOPALLAR (Küme Evler)",
        "adi": "TOPALLAR",
        "kimlikNo": 609159
    },
    {
        "mahalleKayitNo": 159749,
        "turKod": 5,
        "bilesenAdi": "ÜMMETLER (Küme Evler)",
        "adi": "ÜMMETLER",
        "kimlikNo": 623282810
    }
]