[
    {
        "mahalleKayitNo": 194683,
        "turKod": 4,
        "bilesenAdi": "AHIR ÖNÜ (Sokak)",
        "adi": "AHIR ÖNÜ",
        "kimlikNo": 87245
    },
    {
        "mahalleKayitNo": 194683,
        "turKod": 4,
        "bilesenAdi": "BOZUK BAHÇE (Sokak)",
        "adi": "BOZUK BAHÇE",
        "kimlikNo": 575626
    },
    {
        "mahalleKayitNo": 194683,
        "turKod": 4,
        "bilesenAdi": "CAMİYOLU (Sokak)",
        "adi": "CAMİYOLU",
        "kimlikNo": 569929
    },
    {
        "mahalleKayitNo": 194683,
        "turKod": 5,
        "bilesenAdi": "DALLIK YOLU (Küme Evler)",
        "adi": "DALLIK YOLU",
        "kimlikNo": 1277433
    },
    {
        "mahalleKayitNo": 194683,
        "turKod": 4,
        "bilesenAdi": "DEĞİRMENDERE (Sokak)",
        "adi": "DEĞİRMENDERE",
        "kimlikNo": 1089479
    },
    {
        "mahalleKayitNo": 194683,
        "turKod": 5,
        "bilesenAdi": "HALİL BAHÇELİ (Küme Evler)",
        "adi": "HALİL BAHÇELİ",
        "kimlikNo": 825033
    },
    {
        "mahalleKayitNo": 194683,
        "turKod": 4,
        "bilesenAdi": "HANCALI (Sokak)",
        "adi": "HANCALI",
        "kimlikNo": 570803
    },
    {
        "mahalleKayitNo": 194683,
        "turKod": 5,
        "bilesenAdi": "İNCİRLİOVA YOLU (Küme Evler)",
        "adi": "İNCİRLİOVA YOLU",
        "kimlikNo": 1281045
    },
    {
        "mahalleKayitNo": 194683,
        "turKod": 4,
        "bilesenAdi": "KAYABAŞI (Sokak)",
        "adi": "KAYABAŞI",
        "kimlikNo": 569409
    },
    {
        "mahalleKayitNo": 194683,
        "turKod": 5,
        "bilesenAdi": "KIZILYAR (Küme Evler)",
        "adi": "KIZILYAR",
        "kimlikNo": 1089481
    }
]