[
    {
        "mahalleKayitNo": 51594,
        "turKod": 3,
        "bilesenAdi": "ARZOLUK (Cadde)",
        "adi": "ARZOLUK",
        "kimlikNo": 298502
    },
    {
        "mahalleKayitNo": 51594,
        "turKod": 4,
        "bilesenAdi": "ARZOLUK 1. (Sokak)",
        "adi": "ARZOLUK 1.",
        "kimlikNo": 675869
    },
    {
        "mahalleKayitNo": 51594,
        "turKod": 4,
        "bilesenAdi": "BİLNMEYEN69 (Sokak)",
        "adi": "BİLNMEYEN69",
        "kimlikNo": 419585391
    },
    {
        "mahalleKayitNo": 51594,
        "turKod": 4,
        "bilesenAdi": "CUMA YENİYOL5 (Sokak)",
        "adi": "CUMA YENİYOL5",
        "kimlikNo": 566559881
    },
    {
        "mahalleKayitNo": 51594,
        "turKod": 4,
        "bilesenAdi": "ÇIKMAZ SOKAK (Sokak)",
        "adi": "ÇIKMAZ SOKAK",
        "kimlikNo": 504112060
    },
    {
        "mahalleKayitNo": 51594,
        "turKod": 4,
        "bilesenAdi": "DERE (Sokak)",
        "adi": "DERE",
        "kimlikNo": 455402
    },
    {
        "mahalleKayitNo": 51594,
        "turKod": 4,
        "bilesenAdi": "DERE/1 (Sokak)",
        "adi": "DERE/1",
        "kimlikNo": 363396791
    },
    {
        "mahalleKayitNo": 51594,
        "turKod": 4,
        "bilesenAdi": "DERE/2 (Sokak)",
        "adi": "DERE/2",
        "kimlikNo": 808096500
    },
    {
        "mahalleKayitNo": 51594,
        "turKod": 4,
        "bilesenAdi": "DEREBAHÇE (Sokak)",
        "adi": "DEREBAHÇE",
        "kimlikNo": 300192
    },
    {
        "mahalleKayitNo": 51594,
        "turKod": 3,
        "bilesenAdi": "EDAVOĞLU MEHMETBEY (Cadde)",
        "adi": "EDAVOĞLU MEHMETBEY",
        "kimlikNo": 300193
    },
    {
        "mahalleKayitNo": 51594,
        "turKod": 3,
        "bilesenAdi": "ERENLER (Cadde)",
        "adi": "ERENLER",
        "kimlikNo": 370375
    },
    {
        "mahalleKayitNo": 51594,
        "turKod": 4,
        "bilesenAdi": "KADER (Sokak)",
        "adi": "KADER",
        "kimlikNo": 455403
    },
    {
        "mahalleKayitNo": 51594,
        "turKod": 3,
        "bilesenAdi": "KARŞIYAKA (Cadde)",
        "adi": "KARŞIYAKA",
        "kimlikNo": 300194
    },
    {
        "mahalleKayitNo": 51594,
        "turKod": 4,
        "bilesenAdi": "KARŞIYAKA 1 (Sokak)",
        "adi": "KARŞIYAKA 1",
        "kimlikNo": 280780870
    },
    {
        "mahalleKayitNo": 51594,
        "turKod": 4,
        "bilesenAdi": "KARŞIYAKA 2 (Sokak)",
        "adi": "KARŞIYAKA 2",
        "kimlikNo": 573634260
    },
    {
        "mahalleKayitNo": 51594,
        "turKod": 5,
        "bilesenAdi": "KARŞIYAKA 3 (Küme Evler)",
        "adi": "KARŞIYAKA 3",
        "kimlikNo": 201327831
    },
    {
        "mahalleKayitNo": 51594,
        "turKod": 4,
        "bilesenAdi": "KARŞIYAKA 4 (Sokak)",
        "adi": "KARŞIYAKA 4",
        "kimlikNo": 137753661
    },
    {
        "mahalleKayitNo": 51594,
        "turKod": 4,
        "bilesenAdi": "KARŞIYAKA 5 (Sokak)",
        "adi": "KARŞIYAKA 5",
        "kimlikNo": 802006291
    },
    {
        "mahalleKayitNo": 51594,
        "turKod": 4,
        "bilesenAdi": "KARŞIYAKA 6 (Sokak)",
        "adi": "KARŞIYAKA 6",
        "kimlikNo": 775207571
    },
    {
        "mahalleKayitNo": 51594,
        "turKod": 4,
        "bilesenAdi": "KARŞIYAKA 7 (Sokak)",
        "adi": "KARŞIYAKA 7",
        "kimlikNo": 775604800
    },
    {
        "mahalleKayitNo": 51594,
        "turKod": 4,
        "bilesenAdi": "KARŞIYAKA 8 (Sokak)",
        "adi": "KARŞIYAKA 8",
        "kimlikNo": 887248691
    },
    {
        "mahalleKayitNo": 51594,
        "turKod": 5,
        "bilesenAdi": "KARŞIYAKA TEPESİ (Küme Evler)",
        "adi": "KARŞIYAKA TEPESİ",
        "kimlikNo": 300195
    },
    {
        "mahalleKayitNo": 51594,
        "turKod": 4,
        "bilesenAdi": "LEYLAK (Sokak)",
        "adi": "LEYLAK",
        "kimlikNo": 455404
    },
    {
        "mahalleKayitNo": 51594,
        "turKod": 4,
        "bilesenAdi": "MESCİT (Sokak)",
        "adi": "MESCİT",
        "kimlikNo": 288102321
    },
    {
        "mahalleKayitNo": 51594,
        "turKod": 4,
        "bilesenAdi": "MESCİT ARALIĞI (Sokak)",
        "adi": "MESCİT ARALIĞI",
        "kimlikNo": 300196
    },
    {
        "mahalleKayitNo": 51594,
        "turKod": 3,
        "bilesenAdi": "NAMIK KEMAL (Cadde)",
        "adi": "NAMIK KEMAL",
        "kimlikNo": 300197
    },
    {
        "mahalleKayitNo": 51594,
        "turKod": 4,
        "bilesenAdi": "ODUNCUOĞLU (Sokak)",
        "adi": "ODUNCUOĞLU",
        "kimlikNo": 455405
    },
    {
        "mahalleKayitNo": 51594,
        "turKod": 4,
        "bilesenAdi": "ODUNCUOĞLU 1 (Sokak)",
        "adi": "ODUNCUOĞLU 1",
        "kimlikNo": 303900170
    },
    {
        "mahalleKayitNo": 51594,
        "turKod": 4,
        "bilesenAdi": "SAMUR (Sokak)",
        "adi": "SAMUR",
        "kimlikNo": 1490775
    },
    {
        "mahalleKayitNo": 51594,
        "turKod": 3,
        "bilesenAdi": "SERENALTI (Cadde)",
        "adi": "SERENALTI",
        "kimlikNo": 300198
    },
    {
        "mahalleKayitNo": 51594,
        "turKod": 4,
        "bilesenAdi": "SERENALTI 1 (Sokak)",
        "adi": "SERENALTI 1",
        "kimlikNo": 546053811
    },
    {
        "mahalleKayitNo": 51594,
        "turKod": 4,
        "bilesenAdi": "SOFTAOĞLU (Sokak)",
        "adi": "SOFTAOĞLU",
        "kimlikNo": 300200
    },
    {
        "mahalleKayitNo": 51594,
        "turKod": 5,
        "bilesenAdi": "ŞEHİR DIŞI (Küme Evler)",
        "adi": "ŞEHİR DIŞI",
        "kimlikNo": 218951801
    },
    {
        "mahalleKayitNo": 51594,
        "turKod": 4,
        "bilesenAdi": "ŞEHİRDIŞI (Sokak)",
        "adi": "ŞEHİRDIŞI",
        "kimlikNo": 933563501
    },
    {
        "mahalleKayitNo": 51594,
        "turKod": 3,
        "bilesenAdi": "ŞHT.AHMET GÜDER (Cadde)",
        "adi": "ŞHT.AHMET GÜDER",
        "kimlikNo": 455408
    },
    {
        "mahalleKayitNo": 51594,
        "turKod": 4,
        "bilesenAdi": "ŞHT.AHMET GÜDER 2 (Sokak)",
        "adi": "ŞHT.AHMET GÜDER 2",
        "kimlikNo": 494394580
    },
    {
        "mahalleKayitNo": 51594,
        "turKod": 4,
        "bilesenAdi": "ŞHT.AHMET GÜDER/1 (Sokak)",
        "adi": "ŞHT.AHMET GÜDER/1",
        "kimlikNo": 288416411
    },
    {
        "mahalleKayitNo": 51594,
        "turKod": 5,
        "bilesenAdi": "ŞIRŞIR YOLU (Küme Evler)",
        "adi": "ŞIRŞIR YOLU",
        "kimlikNo": 902417871
    },
    {
        "mahalleKayitNo": 51594,
        "turKod": 4,
        "bilesenAdi": "TAMER (Sokak)",
        "adi": "TAMER",
        "kimlikNo": 455406
    },
    {
        "mahalleKayitNo": 51594,
        "turKod": 4,
        "bilesenAdi": "TEKKE (Sokak)",
        "adi": "TEKKE",
        "kimlikNo": 455407
    },
    {
        "mahalleKayitNo": 51594,
        "turKod": 4,
        "bilesenAdi": "TEKKE ÇIKMAZI (Sokak)",
        "adi": "TEKKE ÇIKMAZI",
        "kimlikNo": 300202
    },
    {
        "mahalleKayitNo": 51594,
        "turKod": 3,
        "bilesenAdi": "TEKKE. (Cadde)",
        "adi": "TEKKE.",
        "kimlikNo": 523174351
    },
    {
        "mahalleKayitNo": 51594,
        "turKod": 4,
        "bilesenAdi": "TÜRBE (Sokak)",
        "adi": "TÜRBE",
        "kimlikNo": 300203
    },
    {
        "mahalleKayitNo": 51594,
        "turKod": 4,
        "bilesenAdi": "UZUNPAZAR 1 (Sokak)",
        "adi": "UZUNPAZAR 1",
        "kimlikNo": 537319640
    },
    {
        "mahalleKayitNo": 51594,
        "turKod": 4,
        "bilesenAdi": "YAĞMUR (Sokak)",
        "adi": "YAĞMUR",
        "kimlikNo": 641941291
    },
    {
        "mahalleKayitNo": 51594,
        "turKod": 4,
        "bilesenAdi": "YATIR (Sokak)",
        "adi": "YATIR",
        "kimlikNo": 173365611
    },
    {
        "mahalleKayitNo": 51594,
        "turKod": 3,
        "bilesenAdi": "YUSUF CEMİLBEY (Cadde)",
        "adi": "YUSUF CEMİLBEY",
        "kimlikNo": 300204
    },
    {
        "mahalleKayitNo": 51594,
        "turKod": 4,
        "bilesenAdi": "YUSUF CEMİLBEY 2 (Sokak)",
        "adi": "YUSUF CEMİLBEY 2",
        "kimlikNo": 199088880
    },
    {
        "mahalleKayitNo": 51594,
        "turKod": 4,
        "bilesenAdi": "YUSUF CEMİLBEY 3. (Sokak)",
        "adi": "YUSUF CEMİLBEY 3.",
        "kimlikNo": 684555
    },
    {
        "mahalleKayitNo": 51594,
        "turKod": 4,
        "bilesenAdi": "YUSUF CEMİLBEY 4. (Sokak)",
        "adi": "YUSUF CEMİLBEY 4.",
        "kimlikNo": 455401
    },
    {
        "mahalleKayitNo": 51594,
        "turKod": 4,
        "bilesenAdi": "ZAMBAK (Sokak)",
        "adi": "ZAMBAK",
        "kimlikNo": 300205
    }
]