[
    {
        "mahalleKayitNo": 52160,
        "turKod": 4,
        "bilesenAdi": "115. (Sokak)",
        "adi": "115.",
        "kimlikNo": 306229
    },
    {
        "mahalleKayitNo": 52160,
        "turKod": 4,
        "bilesenAdi": "118. (Sokak)",
        "adi": "118.",
        "kimlikNo": 460706
    },
    {
        "mahalleKayitNo": 52160,
        "turKod": 4,
        "bilesenAdi": "119. (Sokak)",
        "adi": "119.",
        "kimlikNo": 306230
    },
    {
        "mahalleKayitNo": 52160,
        "turKod": 4,
        "bilesenAdi": "120. (Sokak)",
        "adi": "120.",
        "kimlikNo": 306231
    },
    {
        "mahalleKayitNo": 52160,
        "turKod": 4,
        "bilesenAdi": "122. (Sokak)",
        "adi": "122.",
        "kimlikNo": 460707
    },
    {
        "mahalleKayitNo": 52160,
        "turKod": 4,
        "bilesenAdi": "136. (Sokak)",
        "adi": "136.",
        "kimlikNo": 306232
    },
    {
        "mahalleKayitNo": 52160,
        "turKod": 3,
        "bilesenAdi": "144. (MUSTAFA KİRAZOĞLU) (Cadde)",
        "adi": "144. (MUSTAFA KİRAZOĞLU)",
        "kimlikNo": 1497379
    },
    {
        "mahalleKayitNo": 52160,
        "turKod": 4,
        "bilesenAdi": "25. (Sokak)",
        "adi": "25.",
        "kimlikNo": 306233
    },
    {
        "mahalleKayitNo": 52160,
        "turKod": 4,
        "bilesenAdi": "46. (Sokak)",
        "adi": "46.",
        "kimlikNo": 460708
    },
    {
        "mahalleKayitNo": 52160,
        "turKod": 3,
        "bilesenAdi": "50.(HAŞİM HAŞİMOĞLU) (Cadde)",
        "adi": "50.(HAŞİM HAŞİMOĞLU)",
        "kimlikNo": 482712
    },
    {
        "mahalleKayitNo": 52160,
        "turKod": 4,
        "bilesenAdi": "55. (Sokak)",
        "adi": "55.",
        "kimlikNo": 486027
    },
    {
        "mahalleKayitNo": 52160,
        "turKod": 4,
        "bilesenAdi": "68. (Sokak)",
        "adi": "68.",
        "kimlikNo": 512282
    },
    {
        "mahalleKayitNo": 52160,
        "turKod": 4,
        "bilesenAdi": "71. (Sokak)",
        "adi": "71.",
        "kimlikNo": 306234
    },
    {
        "mahalleKayitNo": 52160,
        "turKod": 4,
        "bilesenAdi": "72. (Sokak)",
        "adi": "72.",
        "kimlikNo": 306235
    },
    {
        "mahalleKayitNo": 52160,
        "turKod": 4,
        "bilesenAdi": "73. (Sokak)",
        "adi": "73.",
        "kimlikNo": 460709
    },
    {
        "mahalleKayitNo": 52160,
        "turKod": 4,
        "bilesenAdi": "74. (Sokak)",
        "adi": "74.",
        "kimlikNo": 306236
    },
    {
        "mahalleKayitNo": 52160,
        "turKod": 4,
        "bilesenAdi": "75. (Sokak)",
        "adi": "75.",
        "kimlikNo": 306237
    },
    {
        "mahalleKayitNo": 52160,
        "turKod": 4,
        "bilesenAdi": "76. (Sokak)",
        "adi": "76.",
        "kimlikNo": 306214
    },
    {
        "mahalleKayitNo": 52160,
        "turKod": 4,
        "bilesenAdi": "77. (Sokak)",
        "adi": "77.",
        "kimlikNo": 306215
    },
    {
        "mahalleKayitNo": 52160,
        "turKod": 4,
        "bilesenAdi": "78. (Sokak)",
        "adi": "78.",
        "kimlikNo": 306216
    },
    {
        "mahalleKayitNo": 52160,
        "turKod": 4,
        "bilesenAdi": "79. (Sokak)",
        "adi": "79.",
        "kimlikNo": 460700
    },
    {
        "mahalleKayitNo": 52160,
        "turKod": 4,
        "bilesenAdi": "80. (Sokak)",
        "adi": "80.",
        "kimlikNo": 306217
    },
    {
        "mahalleKayitNo": 52160,
        "turKod": 4,
        "bilesenAdi": "81. (Sokak)",
        "adi": "81.",
        "kimlikNo": 306218
    },
    {
        "mahalleKayitNo": 52160,
        "turKod": 4,
        "bilesenAdi": "82. (Sokak)",
        "adi": "82.",
        "kimlikNo": 460701
    },
    {
        "mahalleKayitNo": 52160,
        "turKod": 4,
        "bilesenAdi": "83. (Sokak)",
        "adi": "83.",
        "kimlikNo": 306219
    },
    {
        "mahalleKayitNo": 52160,
        "turKod": 4,
        "bilesenAdi": "86. (Sokak)",
        "adi": "86.",
        "kimlikNo": 306220
    },
    {
        "mahalleKayitNo": 52160,
        "turKod": 4,
        "bilesenAdi": "87. (Sokak)",
        "adi": "87.",
        "kimlikNo": 460702
    },
    {
        "mahalleKayitNo": 52160,
        "turKod": 4,
        "bilesenAdi": "88. (Sokak)",
        "adi": "88.",
        "kimlikNo": 306221
    },
    {
        "mahalleKayitNo": 52160,
        "turKod": 4,
        "bilesenAdi": "89. (Sokak)",
        "adi": "89.",
        "kimlikNo": 306222
    },
    {
        "mahalleKayitNo": 52160,
        "turKod": 4,
        "bilesenAdi": "90. (Sokak)",
        "adi": "90.",
        "kimlikNo": 306223
    },
    {
        "mahalleKayitNo": 52160,
        "turKod": 4,
        "bilesenAdi": "92. (Sokak)",
        "adi": "92.",
        "kimlikNo": 306224
    },
    {
        "mahalleKayitNo": 52160,
        "turKod": 4,
        "bilesenAdi": "94. (Sokak)",
        "adi": "94.",
        "kimlikNo": 306225
    },
    {
        "mahalleKayitNo": 52160,
        "turKod": 4,
        "bilesenAdi": "95. (Sokak)",
        "adi": "95.",
        "kimlikNo": 460704
    },
    {
        "mahalleKayitNo": 52160,
        "turKod": 4,
        "bilesenAdi": "96. (Sokak)",
        "adi": "96.",
        "kimlikNo": 306226
    },
    {
        "mahalleKayitNo": 52160,
        "turKod": 4,
        "bilesenAdi": "97. (Sokak)",
        "adi": "97.",
        "kimlikNo": 460705
    },
    {
        "mahalleKayitNo": 52160,
        "turKod": 4,
        "bilesenAdi": "98. (Sokak)",
        "adi": "98.",
        "kimlikNo": 306227
    },
    {
        "mahalleKayitNo": 52160,
        "turKod": 4,
        "bilesenAdi": "99. (Sokak)",
        "adi": "99.",
        "kimlikNo": 306228
    },
    {
        "mahalleKayitNo": 52160,
        "turKod": 3,
        "bilesenAdi": "REDDİ İŞGAL CADDESİ (Cadde)",
        "adi": "REDDİ İŞGAL CADDESİ",
        "kimlikNo": 460703
    }
]