[
    {
        "mahalleKayitNo": 99669,
        "turKod": 5,
        "bilesenAdi": "BÜYÜKDÜZ- (Küme Evler)",
        "adi": "BÜYÜKDÜZ-",
        "kimlikNo": 423226
    },
    {
        "mahalleKayitNo": 99669,
        "turKod": 5,
        "bilesenAdi": "EZENLİ SOHU- (Küme Evler)",
        "adi": "EZENLİ SOHU-",
        "kimlikNo": 172910
    },
    {
        "mahalleKayitNo": 99669,
        "turKod": 5,
        "bilesenAdi": "FATIH (Küme Evler)",
        "adi": "FATIH",
        "kimlikNo": 358192
    },
    {
        "mahalleKayitNo": 99669,
        "turKod": 5,
        "bilesenAdi": "İMAM KAYASI- (Küme Evler)",
        "adi": "İMAM KAYASI-",
        "kimlikNo": 358193
    },
    {
        "mahalleKayitNo": 99669,
        "turKod": 5,
        "bilesenAdi": "MEHMETAĞA (Küme Evler)",
        "adi": "MEHMETAĞA",
        "kimlikNo": 116194750
    }
]